pixai/.env
pixai/.pypirc
pixai/LICENSE
pixai/README.md
pixai/Roy.gif
pixai/__init__.py
pixai/cli.py
pixai/file
pixai/gui.py
pixai/launt.gif
pixai/logo.ico
pixai/requirements.txt
pixai/search_history.json
pixai/setup.py
pixai/upload_to_pypi.bat
pixai/Editing/edit.jpg
pixai/PixAi_Setup/asset/asset.exe
pixai/PixAi_Setup/asset/logo.ico
pixai/PixAi_Setup/asset/_internal/VCRUNTIME140.dll
pixai/PixAi_Setup/asset/_internal/VCRUNTIME140_1.dll
pixai/PixAi_Setup/asset/_internal/_asyncio.pyd
pixai/PixAi_Setup/asset/_internal/_brotli.cp312-win_amd64.pyd
pixai/PixAi_Setup/asset/_internal/_bz2.pyd
pixai/PixAi_Setup/asset/_internal/_cffi_backend.cp312-win_amd64.pyd
pixai/PixAi_Setup/asset/_internal/_ctypes.pyd
pixai/PixAi_Setup/asset/_internal/_decimal.pyd
pixai/PixAi_Setup/asset/_internal/_elementtree.pyd
pixai/PixAi_Setup/asset/_internal/_hashlib.pyd
pixai/PixAi_Setup/asset/_internal/_lzma.pyd
pixai/PixAi_Setup/asset/_internal/_multiprocessing.pyd
pixai/PixAi_Setup/asset/_internal/_overlapped.pyd
pixai/PixAi_Setup/asset/_internal/_queue.pyd
pixai/PixAi_Setup/asset/_internal/_socket.pyd
pixai/PixAi_Setup/asset/_internal/_ssl.pyd
pixai/PixAi_Setup/asset/_internal/_tkinter.pyd
pixai/PixAi_Setup/asset/_internal/_wmi.pyd
pixai/PixAi_Setup/asset/_internal/api-ms-win-core-console-l1-1-0.dll
pixai/PixAi_Setup/asset/_internal/api-ms-win-core-datetime-l1-1-0.dll
pixai/PixAi_Setup/asset/_internal/api-ms-win-core-debug-l1-1-0.dll
pixai/PixAi_Setup/asset/_internal/api-ms-win-core-errorhandling-l1-1-0.dll
pixai/PixAi_Setup/asset/_internal/api-ms-win-core-fibers-l1-1-0.dll
pixai/PixAi_Setup/asset/_internal/api-ms-win-core-file-l1-1-0.dll
pixai/PixAi_Setup/asset/_internal/api-ms-win-core-file-l1-2-0.dll
pixai/PixAi_Setup/asset/_internal/api-ms-win-core-file-l2-1-0.dll
pixai/PixAi_Setup/asset/_internal/api-ms-win-core-handle-l1-1-0.dll
pixai/PixAi_Setup/asset/_internal/api-ms-win-core-heap-l1-1-0.dll
pixai/PixAi_Setup/asset/_internal/api-ms-win-core-interlocked-l1-1-0.dll
pixai/pixai.egg-info/PKG-INFO
pixai/pixai.egg-info/SOURCES.txt
pixai/pixai.egg-info/dependency_links.txt
pixai/pixai.egg-info/entry_points.txt
pixai/pixai.egg-info/requires.txt
pixai/pixai.egg-info/top_level.txt
pixai-1.0.0.dist-info/licenses/LICENSE
pixai-1.0.0.dist-info/METADATA
pixai-1.0.0.dist-info/WHEEL
pixai-1.0.0.dist-info/entry_points.txt
pixai-1.0.0.dist-info/top_level.txt
pixai/PixAi_Setup/asset/_internal/cryptography-42.0.8.dist-info/INSTALLER
pixai/PixAi_Setup/asset/_internal/cryptography-42.0.8.dist-info/LICENSE
pixai/PixAi_Setup/asset/_internal/cryptography-42.0.8.dist-info/LICENSE.APACHE
pixai/PixAi_Setup/asset/_internal/cryptography-42.0.8.dist-info/LICENSE.BSD
pixai/PixAi_Setup/asset/_internal/cryptography-42.0.8.dist-info/METADATA
pixai/PixAi_Setup/asset/_internal/cryptography-42.0.8.dist-info/RECORD
pixai/PixAi_Setup/asset/_internal/cryptography-42.0.8.dist-info/WHEEL
pixai/PixAi_Setup/asset/_internal/cryptography-42.0.8.dist-info/top_level.txt
pixai/PixAi_Setup/asset/_internal/pyreadline3-3.5.4.dist-info/INSTALLER
pixai/PixAi_Setup/asset/_internal/pyreadline3-3.5.4.dist-info/LICENSE.md
pixai/PixAi_Setup/asset/_internal/pyreadline3-3.5.4.dist-info/METADATA
pixai/PixAi_Setup/asset/_internal/pyreadline3-3.5.4.dist-info/RECORD
pixai/PixAi_Setup/asset/_internal/pyreadline3-3.5.4.dist-info/WHEEL
pixai/PixAi_Setup/asset/_internal/pyreadline3-3.5.4.dist-info/top_level.txt
pixai/PixAi_Setup/asset/_internal/setuptools/_vendor/importlib_metadata-8.0.0.dist-info/INSTALLER
pixai/PixAi_Setup/asset/_internal/setuptools/_vendor/importlib_metadata-8.0.0.dist-info/LICENSE
pixai/PixAi_Setup/asset/_internal/setuptools/_vendor/importlib_metadata-8.0.0.dist-info/METADATA
pixai/PixAi_Setup/asset/_internal/setuptools/_vendor/importlib_metadata-8.0.0.dist-info/RECORD
pixai/PixAi_Setup/asset/_internal/setuptools/_vendor/importlib_metadata-8.0.0.dist-info/REQUESTED
pixai/PixAi_Setup/asset/_internal/setuptools/_vendor/importlib_metadata-8.0.0.dist-info/WHEEL
pixai/PixAi_Setup/asset/_internal/setuptools/_vendor/importlib_metadata-8.0.0.dist-info/top_level.txt
pixai-1.0.0.dist-info/RECORD
